{
  "generated_at": "2026-05-13T20:14:46.338169",
  "account_summary": {
    "starting_capital": 200.0,
    "current_cash": 200.0,
    "portfolio_value": 200.0,
    "total_pnl": 0.0,
    "return_pct": 0.0
  },
  "trading_stats": {
    "total_trades": 6,
    "completed_trades": 6,
    "active_trades": 0,
    "rejected_signals": 0,
    "wins": 2,
    "losses": 4,
    "win_rate_pct": 33.33333333333333,
    "total_pnl": 0.3020004153251721,
    "avg_win": 9.81750017404557,
    "avg_loss": -4.833249983191491,
    "profit_factor": 2.0312419610381665
  },
  "trades": [
    {
      "ticker": "SPCE",
      "entry_time": "2026-05-13T18:41:56.665811",
      "entry_price": 3.069999933242798,
      "shares": 32,
      "stop_loss": 2.916499936580658,
      "take_profit": 3.376999926567078,
      "signal_type": "runner_vwap",
      "signal_date": "2026-04-06",
      "score": 7.0,
      "gap_pct": 10.162601468425821,
      "vol_mult": 6.24819046426111,
      "status": "closed",
      "orders": {
        "entry": "PAPER-1",
        "stop": "PAPER-2",
        "target": "PAPER-3"
      },
      "market_regime": "risk_on",
      "vix_level": 17.8700008392334,
      "risk_dollars": 5.0,
      "signal_id": "SPCE_2026-04-06_1778722916.665811",
      "fill_id": "fill_SPCE_2026-04-06_1778722916.665811_1778722916.67133",
      "signal_quality": "perfect",
      "exit_time": "2026-05-13T00:00:00-04:00",
      "exit_price": 2.916499936580658,
      "exit_reason": "STOP",
      "pnl": -4.911999893188479,
      "return_pct": -5.000000000000004,
      "pnl_pct": -5.000000000000004,
      "hold_days": 0,
      "phase25_outcome_synced": true
    },
    {
      "ticker": "SPCE",
      "entry_time": "2026-05-13T18:45:22.634893",
      "entry_price": 2.430000066757202,
      "shares": 41,
      "stop_loss": 2.3085000634193418,
      "take_profit": 2.6730000734329225,
      "signal_type": "runner_vwap",
      "signal_date": "2026-03-31",
      "score": 7.0,
      "gap_pct": 11.52073692213711,
      "vol_mult": 8.810559296670407,
      "status": "closed",
      "orders": {
        "entry": "PAPER-1",
        "stop": "PAPER-2",
        "target": "PAPER-3"
      },
      "market_regime": "risk_on",
      "vix_level": 17.8700008392334,
      "risk_dollars": 5.0,
      "signal_id": "SPCE_2026-03-31_1778723122.634893",
      "fill_id": "fill_SPCE_2026-03-31_1778723122.634893_1778723122.64125",
      "signal_quality": "perfect",
      "exit_time": "2026-05-13T00:00:00-04:00",
      "exit_price": 2.6730000734329225,
      "exit_reason": "TARGET",
      "pnl": 9.963000273704532,
      "return_pct": 10.000000000000009,
      "pnl_pct": 10.000000000000009,
      "hold_days": 0,
      "phase25_outcome_synced": true
    },
    {
      "ticker": "COMP",
      "entry_time": "2026-05-13T18:47:36.257124",
      "entry_price": 7.440000057220459,
      "shares": 13,
      "stop_loss": 7.068000054359436,
      "take_profit": 8.184000062942506,
      "signal_type": "runner_vwap",
      "signal_date": "2026-04-08",
      "score": 5.0,
      "gap_pct": 9.880244628889693,
      "vol_mult": 2.096140898461661,
      "status": "closed",
      "orders": {
        "entry": "PAPER-1",
        "stop": "PAPER-2",
        "target": "PAPER-3"
      },
      "market_regime": "risk_on",
      "vix_level": 17.8700008392334,
      "risk_dollars": 5.0,
      "signal_id": "COMP_2026-04-08_1778723256.257124",
      "fill_id": "fill_COMP_2026-04-08_1778723256.257124_1778723256.262478",
      "signal_quality": "good",
      "exit_time": "2026-05-13T00:00:00-04:00",
      "exit_price": 8.184000062942506,
      "exit_reason": "TARGET",
      "pnl": 9.672000074386606,
      "return_pct": 10.000000000000009,
      "pnl_pct": 10.000000000000009,
      "hold_days": 0,
      "phase25_outcome_synced": true
    },
    {
      "ticker": "INTR",
      "entry_time": "2026-05-13T18:50:21.335660",
      "entry_price": 8.149999618530273,
      "shares": 12,
      "stop_loss": 7.74249963760376,
      "take_profit": 8.964999580383301,
      "signal_type": "runner_vwap",
      "signal_date": "2026-04-08",
      "score": 5.0,
      "gap_pct": 9.419348932081654,
      "vol_mult": 2.1590750387034854,
      "status": "closed",
      "orders": {
        "entry": "PAPER-1",
        "stop": "PAPER-2",
        "target": "PAPER-3"
      },
      "market_regime": "risk_on",
      "vix_level": 17.8700008392334,
      "risk_dollars": 5.0,
      "signal_id": "INTR_2026-04-08_1778723421.33566",
      "fill_id": "fill_INTR_2026-04-08_1778723421.33566_1778723421.374828",
      "signal_quality": "good",
      "exit_time": "2026-05-13T00:00:00-04:00",
      "exit_price": 7.74249963760376,
      "exit_reason": "STOP",
      "pnl": -4.889999771118166,
      "return_pct": -5.000000000000004,
      "pnl_pct": -5.000000000000004,
      "hold_days": 0,
      "phase25_outcome_synced": true
    },
    {
      "ticker": "TLRY",
      "entry_time": "2026-05-13T19:32:30.507004",
      "entry_price": 9.180000305175781,
      "shares": 10,
      "stop_loss": 8.721000289916992,
      "take_profit": 10.09800033569336,
      "signal_type": "runner_vwap",
      "signal_date": "2026-01-09",
      "score": 5.5,
      "gap_pct": 10.076671026967256,
      "vol_mult": 2.507678075855689,
      "status": "closed",
      "orders": {
        "entry": "PAPER-1",
        "stop": "PAPER-2",
        "target": "PAPER-3"
      },
      "market_regime": "risk_on",
      "vix_level": 17.8700008392334,
      "risk_dollars": 5.0,
      "signal_id": "TLRY_2026-01-09_1778725950.507004",
      "fill_id": "fill_TLRY_2026-01-09_1778725950.507004_1778725950.519083",
      "signal_quality": "good",
      "exit_time": "2026-05-13T00:00:00-04:00",
      "exit_price": 8.721000289916992,
      "exit_reason": "STOP",
      "pnl": -4.590000152587894,
      "return_pct": -5.000000000000004,
      "pnl_pct": -5.000000000000004,
      "hold_days": 0,
      "phase25_outcome_synced": true
    },
    {
      "ticker": "CGC",
      "entry_time": "2026-05-13T19:36:17.711198",
      "entry_price": 1.2200000286102295,
      "shares": 81,
      "stop_loss": 1.159000027179718,
      "take_profit": 1.3420000314712526,
      "signal_type": "runner_vwap",
      "signal_date": "2026-04-23",
      "score": 6.5,
      "gap_pct": 9.42028954208861,
      "vol_mult": 3.5368286348752305,
      "status": "closed",
      "orders": {
        "entry": "PAPER-1",
        "stop": "PAPER-2",
        "target": "PAPER-3"
      },
      "market_regime": "risk_on",
      "vix_level": 17.8700008392334,
      "risk_dollars": 5.0,
      "signal_id": "CGC_2026-04-23_1778726177.711198",
      "fill_id": "fill_CGC_2026-04-23_1778726177.711198_1778726177.721232",
      "signal_quality": "good",
      "exit_time": "2026-05-13T00:00:00-04:00",
      "exit_price": 1.159000027179718,
      "exit_reason": "STOP",
      "pnl": -4.941000115871426,
      "return_pct": -4.999999999999993,
      "pnl_pct": -4.999999999999993,
      "hold_days": 0,
      "phase25_outcome_synced": true
    }
  ],
  "rejected_signals": [],
  "scan_near_misses": [
    {
      "ticker": "EVGO",
      "date": "2026-04-08",
      "gap_pct": 7.777783811828397,
      "vol_spike": 1.0982176284834455,
      "reason": "gap_outside_sweet_spot",
      "target_gap_range": "9-15"
    },
    {
      "ticker": "SPCE",
      "date": "2026-04-08",
      "gap_pct": 10.200671096467904,
      "vol_spike": 1.191187565733896,
      "reason": "volume_outside_sweet_spot",
      "target_volume_rule": ">= 2.0x"
    },
    {
      "ticker": "ACHR",
      "date": "2026-04-08",
      "gap_pct": 7.865169743308028,
      "vol_spike": 1.0268051237571305,
      "reason": "gap_outside_sweet_spot",
      "target_gap_range": "9-15"
    },
    {
      "ticker": "NIO",
      "date": "2026-02-05",
      "gap_pct": 7.657660995633826,
      "vol_spike": 2.6629714127489086,
      "reason": "gap_outside_sweet_spot",
      "target_gap_range": "9-15"
    },
    {
      "ticker": "BBAI",
      "date": "2026-04-08",
      "gap_pct": 9.275360255651057,
      "vol_spike": 0.9278415013269016,
      "reason": "volume_outside_sweet_spot",
      "target_volume_rule": ">= 2.0x"
    },
    {
      "ticker": "ADT",
      "date": "2026-05-13",
      "gap_pct": 1.0263884613241374,
      "vol_spike": 0.636115063934821,
      "reason": "blocklisted"
    },
    {
      "ticker": "COMP",
      "date": "2026-04-08",
      "gap_pct": 9.880244628889693,
      "vol_spike": 2.096140898461661,
      "reason": "already_processed"
    },
    {
      "ticker": "NVAX",
      "date": "2026-04-08",
      "gap_pct": 7.393479628327546,
      "vol_spike": 1.04549314841961,
      "reason": "gap_outside_sweet_spot",
      "target_gap_range": "9-15"
    },
    {
      "ticker": "INTR",
      "date": "2026-04-08",
      "gap_pct": 9.419348932081654,
      "vol_spike": 2.1590750387034854,
      "reason": "already_processed"
    },
    {
      "ticker": "TLRY",
      "date": "2026-01-09",
      "gap_pct": 10.076671026967256,
      "vol_spike": 2.507678075855689,
      "reason": "already_processed"
    },
    {
      "ticker": "CGC",
      "date": "2026-04-23",
      "gap_pct": 9.42028954208861,
      "vol_spike": 3.5368286348752305,
      "reason": "already_processed"
    },
    {
      "ticker": "OGI",
      "date": "2026-03-05",
      "gap_pct": 7.913670175336283,
      "vol_spike": 2.4289969312232986,
      "reason": "gap_outside_sweet_spot",
      "target_gap_range": "9-15"
    }
  ]
}