{
  "portfolio_run_id": "portfolio_4dd12e2f6b88",
  "timestamp_utc": "2026-05-15T18:33:47.810457+00:00",
  "config_file": "C:\\Users\\kay\\Documents\\Projects\\AutoTrader\\Autotrader\\configs\\_sweep_tmkfevhm.yaml",
  "coordination_mode": "priority_gating",
  "total_trades": 12,
  "gated_signals_count": 0,
  "portfolio_net_pnl": -2.805312211997696,
  "portfolio_profit_factor": 0.7980832857199822,
  "max_simultaneous_assets": 2,
  "report_file": "C:\\Users\\kay\\Documents\\Projects\\AutoTrader\\Autotrader\\reports\\crypto\\sweep_runs\\portfolio_4dd12e2f6b88.json",
  "notes": ""
}